torchregression/__init__.py
torchregression/method.py
torchregression/regression.py
torchregression-0.0.1.dist-info/METADATA
torchregression-0.0.1.dist-info/WHEEL
torchregression-0.0.1.dist-info/top_level.txt
torchregression-0.0.1.dist-info/RECORD
