Metadata-Version: 2.1
Name: torchregression
Version: 0.0.1
Summary: Regression using pyTorch
Home-page: UNKNOWN
Author: Rohan Mohapatra
Author-email: rohan.mohapatra@sjsu.edu
License: UNKNOWN
Platform: UNKNOWN
Classifier: Programming Language :: Python :: 3
Classifier: License :: OSI Approved :: MIT License
Classifier: Operating System :: OS Independent
Requires-Python: >=3.7
